{
    "tasa_cambio": 508.6,
    "porcentaje_descuento": 0,
    "subtotal_usd": 200,
    "subtotal_antes_desc_ves": 101720,
    "monto_descuento_ves": 0,
    "monto_descuento_gravado_ves": 0,
    "monto_descuento_exento_ves": 0,
    "total_gravado_ves": 0,
    "total_exento_ves": 101720,
    "suma_gravado_exento_ves": 101720,
    "subtotal_ves": 101720,
    "coinciden_ves": "SI",
    "total_iva_ves": 0,
    "total_pagar_ves": 101720,
    "verificacion_5porciento": 5086,
    "diferencia_con_debug": 5086
}