{
    "documentoElectronico": {
        "Encabezado": {
            "IdentificacionDocumento": {
                "TipoDocumento": "01",
                "NumeroDocumento": "2213",
                "TipoProveedor": null,
                "TipoTransaccion": null,
                "NumeroPlanillaImportacion": null,
                "NumeroExpedienteImportacion": null,
                "SerieFacturaAfectada": null,
                "NumeroFacturaAfectada": null,
                "FechaFacturaAfectada": null,
                "MontoFacturaAfectada": null,
                "ComentarioFacturaAfectada": null,
                "RegimenEspTributacion": null,
                "FechaEmision": "22\/04\/2026",
                "FechaVencimiento": "22\/04\/2026",
                "HoraEmision": "05:47:48 pm",
                "Anulado": false,
                "TipoDePago": "CREDITO 21 DIAS",
                "Serie": "",
                "Sucursal": "",
                "TipoDeVenta": "Interna",
                "Moneda": "USD"
            },
            "Vendedor": {
                "Codigo": "V3",
                "Nombre": "CAROLINA ZU\u00d1IGA",
                "NumCajero": "V3"
            },
            "Comprador": {
                "TipoIdentificacion": "J",
                "NumeroIdentificacion": "309997807",
                "RazonSocial": "DROGUERIA JOSKAR,C.A",
                "Direccion": "AV.OLIMPICA CON CALLE CEDE\u00d1O CASA 7-16 URB LA CAROLINA BARINAS- BARINAS",
                "Ubigeo": null,
                "Pais": "VE",
                "Notificar": null,
                "Telefono": [
                    "0412-9752737"
                ],
                "Correo": [
                    "compras@drogueriajoskar.com",
                    "ventas.zona4@gruposolsumed.com"
                ],
                "OtrosEnvios": null
            },
            "SujetoRetenido": null,
            "Tercero": null,
            "Totales": {
                "NroItems": "5",
                "MontoGravadoTotal": "112481.59",
                "MontoExentoTotal": "0.00",
                "Subtotal": "112481.59",
                "TotalIVA": "17996.89",
                "MontoTotalConIVA": "130478.48",
                "TotalAPagar": "130478.48",
                "TotalDescuento": "28120.34",
                "SubtotalAntesDescuento": "140601.93",
                "MontoEnLetras": "",
                "ListaDescBonificacion": [
                    {
                        "descDescuento": "Descuento global",
                        "montoDescuento": "28120.34"
                    }
                ],
                "ImpuestosSubtotal": [
                    {
                        "CodigoTotalImp": "G",
                        "AlicuotaImp": "16.00",
                        "BaseImponibleImp": "112480.58",
                        "ValorTotalImp": "17996.89"
                    }
                ],
                "FormasPago": [
                    {
                        "Descripcion": "TRANSFERENCIA BANCARIA",
                        "Fecha": "22\/04\/2026",
                        "Forma": "03",
                        "Monto": "130478.48",
                        "Moneda": "VES",
                        "TipoCambio": "1.0000"
                    }
                ]
            },
            "TotalesOtraMoneda": {
                "Moneda": "USD",
                "TipoCambio": "482.7700",
                "MontoGravadoTotal": "232.99",
                "MontoExentoTotal": "0.00",
                "Subtotal": "232.99",
                "TotalAPagar": "270.27",
                "TotalIVA": "37.28",
                "MontoTotalConIVA": "270.27",
                "TotalDescuento": "58.25",
                "SubtotalAntesDescuento": "291.24",
                "MontoEnLetras": "",
                "ListaDescBonificacion": [
                    {
                        "descDescuento": "Descuento global",
                        "montoDescuento": "58.25"
                    }
                ],
                "ImpuestosSubtotal": [
                    {
                        "CodigoTotalImp": "G",
                        "AlicuotaImp": "16.00",
                        "BaseImponibleImp": "232.99",
                        "ValorTotalImp": "37.28"
                    }
                ],
                "FormasPago": [
                    {
                        "Descripcion": "TRANSFERENCIA BANCARIA",
                        "Fecha": "22\/04\/2026",
                        "Forma": "03",
                        "Monto": "270.27",
                        "Moneda": "USD",
                        "TipoCambio": "1.0000"
                    }
                ]
            }
        },
        "DetallesItems": [
            {
                "NumeroLinea": "1",
                "CodigoCIIU": "0198",
                "CodigoPLU": "MQD-0018",
                "IndicadorBienoServicio": "1",
                "Descripcion": "GUATA ORTOPEDICA 4\" X 3 YDS (10CM) PAQ 12 UNDS",
                "Cantidad": "6.00",
                "UnidadMedida": "UNI",
                "PrecioUnitario": "17.02",
                "PrecioItem": "102.12",
                "CodigoImpuesto": "G",
                "TasaIVA": "16.00",
                "ValorIVA": "16.34",
                "ValorTotalItem": "118.46",
                "InfoAdicionalItem": [
                    {
                        "campo": "Marca",
                        "valor": "SEBIS"
                    }
                ]
            },
            {
                "NumeroLinea": "2",
                "CodigoCIIU": "0198",
                "CodigoPLU": "MQD-0441",
                "IndicadorBienoServicio": "1",
                "Descripcion": "JERINGA 60 CC SIN AGUJA TIPO TOMMY X UND",
                "Cantidad": "50.00",
                "UnidadMedida": "UNI",
                "PrecioUnitario": "0.33",
                "PrecioItem": "16.50",
                "CodigoImpuesto": "G",
                "TasaIVA": "16.00",
                "ValorIVA": "2.64",
                "ValorTotalItem": "19.14",
                "InfoAdicionalItem": [
                    {
                        "campo": "Marca",
                        "valor": "BIALY"
                    }
                ]
            },
            {
                "NumeroLinea": "3",
                "CodigoCIIU": "0198",
                "CodigoPLU": "MQD-0262",
                "IndicadorBienoServicio": "1",
                "Descripcion": "JERINGA DE INSULINA 0.5 ML 30G X 1\/2 CAJA X 100 UDS.",
                "Cantidad": "2.00",
                "UnidadMedida": "UNI",
                "PrecioUnitario": "19.06",
                "PrecioItem": "38.12",
                "CodigoImpuesto": "G",
                "TasaIVA": "16.00",
                "ValorIVA": "6.10",
                "ValorTotalItem": "44.22",
                "InfoAdicionalItem": [
                    {
                        "campo": "Marca",
                        "valor": "GROSSMED"
                    }
                ]
            },
            {
                "NumeroLinea": "4",
                "CodigoCIIU": "0198",
                "CodigoPLU": "MQD-0099",
                "IndicadorBienoServicio": "1",
                "Descripcion": "PATO CLINICO DESCARTABLE",
                "Cantidad": "10.00",
                "UnidadMedida": "UNI",
                "PrecioUnitario": "6.90",
                "PrecioItem": "69.00",
                "CodigoImpuesto": "G",
                "TasaIVA": "16.00",
                "ValorIVA": "11.04",
                "ValorTotalItem": "80.04",
                "InfoAdicionalItem": [
                    {
                        "campo": "Marca",
                        "valor": "GENERICO"
                    }
                ]
            },
            {
                "NumeroLinea": "5",
                "CodigoCIIU": "0198",
                "CodigoPLU": "MIS-0037",
                "IndicadorBienoServicio": "1",
                "Descripcion": "PERA VAGINAL CON CANULA FLEXIBLE",
                "Cantidad": "10.00",
                "UnidadMedida": "UNI",
                "PrecioUnitario": "6.55",
                "PrecioItem": "65.50",
                "CodigoImpuesto": "G",
                "TasaIVA": "16.00",
                "ValorIVA": "10.48",
                "ValorTotalItem": "75.98",
                "InfoAdicionalItem": [
                    {
                        "campo": "Marca",
                        "valor": "INTIMATE"
                    }
                ]
            }
        ],
        "DetallesRetencion": null,
        "Viajes": null,
        "InfoAdicional": [
            {
                "campo": "TransporteCliente",
                "valor": "INTERNO"
            },
            {
                "campo": "ZonaCliente",
                "valor": "BARINAS"
            },
            {
                "campo": "DireccionEntregaCliente",
                "valor": "AV.OLIMPICA CON CALLE CEDE\u00d1O CASA 7-16 URB LA CAROLINA BARINAS- BARINAS"
            }
        ],
        "GuiaDespacho": null,
        "Transporte": null,
        "EsLote": null,
        "EsMinimo": null
    }
}