{
    "documentoElectronico": {
        "Encabezado": {
            "IdentificacionDocumento": {
                "TipoDocumento": "01",
                "NumeroDocumento": "2784",
                "TipoProveedor": null,
                "TipoTransaccion": null,
                "NumeroPlanillaImportacion": null,
                "NumeroExpedienteImportacion": null,
                "SerieFacturaAfectada": null,
                "NumeroFacturaAfectada": null,
                "FechaFacturaAfectada": null,
                "MontoFacturaAfectada": null,
                "ComentarioFacturaAfectada": null,
                "RegimenEspTributacion": null,
                "FechaEmision": "19\/05\/2026",
                "FechaVencimiento": "19\/05\/2026",
                "HoraEmision": "02:48:56 pm",
                "Anulado": false,
                "TipoDePago": "CREDITO 15 DIAS",
                "Serie": "",
                "Sucursal": "",
                "TipoDeVenta": "Interna",
                "Moneda": "USD"
            },
            "Vendedor": {
                "Codigo": "V5",
                "Nombre": "VERONICA DE ABREU",
                "NumCajero": "V5"
            },
            "Comprador": {
                "TipoIdentificacion": "J",
                "NumeroIdentificacion": "503255730",
                "RazonSocial": "FARMACIA GRUPO FARMAVITAL, C.A",
                "Direccion": "CALLE 16 ENTRE AVENIDAS 4TA Y 5TA CC AKRAN AL HALAH NIVEL PB LOCAL 8 SECTOR EL PANTEON SAN FELIPE YARACUY ZONA POSTAL 3201",
                "Ubigeo": null,
                "Pais": "VE",
                "Notificar": null,
                "Telefono": [
                    "0424-5842672"
                ],
                "Correo": [
                    "grupofarmavitaladm@gmail.com",
                    "ventas.zona2@gruposolsumed.com"
                ],
                "OtrosEnvios": null
            },
            "SujetoRetenido": null,
            "Tercero": null,
            "Totales": {
                "NroItems": "9",
                "MontoGravadoTotal": "44472.05",
                "MontoExentoTotal": "45129.85",
                "Subtotal": "89601.90",
                "TotalIVA": "7115.53",
                "MontoTotalConIVA": "96717.43",
                "TotalAPagar": "96717.43",
                "TotalDescuento": "0.00",
                "SubtotalAntesDescuento": "89601.90",
                "MontoEnLetras": "",
                "ListaDescBonificacion": [],
                "ImpuestosSubtotal": [
                    {
                        "CodigoTotalImp": "G",
                        "AlicuotaImp": "16.00",
                        "BaseImponibleImp": "44472.05",
                        "ValorTotalImp": "7115.53"
                    },
                    {
                        "CodigoTotalImp": "E",
                        "AlicuotaImp": "0.00",
                        "BaseImponibleImp": "45129.85",
                        "ValorTotalImp": "0.00"
                    }
                ],
                "FormasPago": [
                    {
                        "Descripcion": "TRANSFERENCIA BANCARIA",
                        "Fecha": "19\/05\/2026",
                        "Forma": "03",
                        "Monto": "96717.43",
                        "Moneda": "VES",
                        "TipoCambio": "1.0000"
                    }
                ]
            },
            "TotalesOtraMoneda": {
                "Moneda": "USD",
                "TipoCambio": "517.9600",
                "MontoGravadoTotal": "85.86",
                "MontoExentoTotal": "87.13",
                "Subtotal": "172.99",
                "TotalAPagar": "186.73",
                "TotalIVA": "13.74",
                "MontoTotalConIVA": "186.73",
                "TotalDescuento": "0.00",
                "SubtotalAntesDescuento": "172.99",
                "MontoEnLetras": "",
                "ListaDescBonificacion": [],
                "ImpuestosSubtotal": [
                    {
                        "CodigoTotalImp": "G",
                        "AlicuotaImp": "16.00",
                        "BaseImponibleImp": "85.86",
                        "ValorTotalImp": "13.74"
                    },
                    {
                        "CodigoTotalImp": "E",
                        "AlicuotaImp": "0.00",
                        "BaseImponibleImp": "87.13",
                        "ValorTotalImp": "0.00"
                    }
                ],
                "FormasPago": [
                    {
                        "Descripcion": "TRANSFERENCIA BANCARIA",
                        "Fecha": "19\/05\/2026",
                        "Forma": "03",
                        "Monto": "186.73",
                        "Moneda": "USD",
                        "TipoCambio": "1.0000"
                    }
                ]
            }
        },
        "DetallesItems": [
            {
                "NumeroLinea": "1",
                "CodigoCIIU": "0198",
                "CodigoPLU": "MQD-0390",
                "IndicadorBienoServicio": "1",
                "Descripcion": "KIT CITOLOGICO CON LAMINA ESMERILADA TALLA S",
                "Cantidad": "10.00",
                "UnidadMedida": "UNI",
                "PrecioUnitario": "2.96",
                "PrecioItem": "29.60",
                "CodigoImpuesto": "G",
                "TasaIVA": "16.00",
                "ValorIVA": "4.74",
                "ValorTotalItem": "34.34",
                "InfoAdicionalItem": [
                    {
                        "campo": "Marca",
                        "valor": "CEPILAB"
                    }
                ]
            },
            {
                "NumeroLinea": "2",
                "CodigoCIIU": "0198",
                "CodigoPLU": "CH-0023",
                "IndicadorBienoServicio": "1",
                "Descripcion": "LEUKOMED SORBACT 5 CM X 7.20 CM",
                "Cantidad": "10.00",
                "UnidadMedida": "UNI",
                "PrecioUnitario": "5.26",
                "PrecioItem": "52.60",
                "CodigoImpuesto": "E",
                "TasaIVA": "0.00",
                "ValorIVA": "0.00",
                "ValorTotalItem": "52.60",
                "InfoAdicionalItem": [
                    {
                        "campo": "Marca",
                        "valor": "BSN"
                    }
                ]
            },
            {
                "NumeroLinea": "3",
                "CodigoCIIU": "0198",
                "CodigoPLU": "CH-0008",
                "IndicadorBienoServicio": "1",
                "Descripcion": "LEUKOMED T PLUS 5 CM X 7.2 CM 1 SOBRE",
                "Cantidad": "5.00",
                "UnidadMedida": "UNI",
                "PrecioUnitario": "2.81",
                "PrecioItem": "14.05",
                "CodigoImpuesto": "G",
                "TasaIVA": "16.00",
                "ValorIVA": "2.25",
                "ValorTotalItem": "16.30",
                "InfoAdicionalItem": [
                    {
                        "campo": "Marca",
                        "valor": "BSN"
                    }
                ]
            },
            {
                "NumeroLinea": "4",
                "CodigoCIIU": "0198",
                "CodigoPLU": "EQ-0067",
                "IndicadorBienoServicio": "1",
                "Descripcion": "NEBULIZADOR PORTATIL C\/CABLE USB",
                "Cantidad": "1.00",
                "UnidadMedida": "UNI",
                "PrecioUnitario": "19.04",
                "PrecioItem": "19.04",
                "CodigoImpuesto": "G",
                "TasaIVA": "16.00",
                "ValorIVA": "3.05",
                "ValorTotalItem": "22.09",
                "InfoAdicionalItem": [
                    {
                        "campo": "Marca",
                        "valor": "GENERICO"
                    }
                ]
            },
            {
                "NumeroLinea": "5",
                "CodigoCIIU": "0198",
                "CodigoPLU": "SOP-0087",
                "IndicadorBienoServicio": "1",
                "Descripcion": "PLANTILLA 100% GEL AZUL TALLA M PAR",
                "Cantidad": "1.00",
                "UnidadMedida": "UNI",
                "PrecioUnitario": "7.35",
                "PrecioItem": "7.35",
                "CodigoImpuesto": "G",
                "TasaIVA": "16.00",
                "ValorIVA": "1.18",
                "ValorTotalItem": "8.53",
                "InfoAdicionalItem": [
                    {
                        "campo": "Marca",
                        "valor": "GENERICO"
                    }
                ]
            },
            {
                "NumeroLinea": "6",
                "CodigoCIIU": "0198",
                "CodigoPLU": "SOP-0085",
                "IndicadorBienoServicio": "1",
                "Descripcion": "PLANTILLA TALONERA TALLA L PAR",
                "Cantidad": "2.00",
                "UnidadMedida": "UNI",
                "PrecioUnitario": "7.91",
                "PrecioItem": "15.82",
                "CodigoImpuesto": "G",
                "TasaIVA": "16.00",
                "ValorIVA": "2.53",
                "ValorTotalItem": "18.35",
                "InfoAdicionalItem": [
                    {
                        "campo": "Marca",
                        "valor": "GENERICO"
                    }
                ]
            },
            {
                "NumeroLinea": "7",
                "CodigoCIIU": "0198",
                "CodigoPLU": "CAT-0008",
                "IndicadorBienoServicio": "1",
                "Descripcion": "SONDA FOLEY 2 VIAS DE LATEX NRO 16FR CAJA 10 UNDS",
                "Cantidad": "1.00",
                "UnidadMedida": "UNI",
                "PrecioUnitario": "11.51",
                "PrecioItem": "11.51",
                "CodigoImpuesto": "E",
                "TasaIVA": "0.00",
                "ValorIVA": "0.00",
                "ValorTotalItem": "11.51",
                "InfoAdicionalItem": [
                    {
                        "campo": "Marca",
                        "valor": "BIALY"
                    }
                ]
            },
            {
                "NumeroLinea": "8",
                "CodigoCIIU": "0198",
                "CodigoPLU": "CAT-0009",
                "IndicadorBienoServicio": "1",
                "Descripcion": "SONDA FOLEY 2 VIAS DE LATEX NRO 18FR CAJA 10 UNDS",
                "Cantidad": "1.00",
                "UnidadMedida": "UNI",
                "PrecioUnitario": "11.51",
                "PrecioItem": "11.51",
                "CodigoImpuesto": "E",
                "TasaIVA": "0.00",
                "ValorIVA": "0.00",
                "ValorTotalItem": "11.51",
                "InfoAdicionalItem": [
                    {
                        "campo": "Marca",
                        "valor": "BIALY"
                    }
                ]
            },
            {
                "NumeroLinea": "9",
                "CodigoCIIU": "0198",
                "CodigoPLU": "CAT-0010",
                "IndicadorBienoServicio": "1",
                "Descripcion": "SONDA FOLEY 2 VIAS DE LATEX NRO 20FR CAJA 10 UNDS",
                "Cantidad": "1.00",
                "UnidadMedida": "UNI",
                "PrecioUnitario": "11.51",
                "PrecioItem": "11.51",
                "CodigoImpuesto": "E",
                "TasaIVA": "0.00",
                "ValorIVA": "0.00",
                "ValorTotalItem": "11.51",
                "InfoAdicionalItem": [
                    {
                        "campo": "Marca",
                        "valor": "BIALY"
                    }
                ]
            }
        ],
        "DetallesRetencion": null,
        "Viajes": null,
        "InfoAdicional": [
            {
                "campo": "TransporteCliente",
                "valor": "INTERNO"
            },
            {
                "campo": "ZonaCliente",
                "valor": "YARACUY"
            },
            {
                "campo": "DireccionEntregaCliente",
                "valor": "CALLE 16 ENTRE AVENIDAS 4TA Y 5TA CC AKRAN AL HALAH NIVEL PB LOCAL 8 SECTOR EL PANTEON SAN FELIPE YARACUY ZONA POSTAL 3201"
            }
        ],
        "GuiaDespacho": null,
        "Transporte": null,
        "EsLote": null,
        "EsMinimo": null
    }
}