{
    "documentoElectronico": {
        "Encabezado": {
            "IdentificacionDocumento": {
                "TipoDocumento": "01",
                "NumeroDocumento": "3541",
                "TipoProveedor": null,
                "TipoTransaccion": null,
                "NumeroPlanillaImportacion": null,
                "NumeroExpedienteImportacion": null,
                "SerieFacturaAfectada": null,
                "NumeroFacturaAfectada": null,
                "FechaFacturaAfectada": null,
                "MontoFacturaAfectada": null,
                "ComentarioFacturaAfectada": null,
                "RegimenEspTributacion": null,
                "FechaEmision": "17\/06\/2026",
                "FechaVencimiento": "17\/06\/2026",
                "HoraEmision": "10:23:25 pm",
                "Anulado": false,
                "TipoDePago": "CONTADO",
                "Serie": "",
                "Sucursal": "",
                "TipoDeVenta": "Interna",
                "Moneda": "USD"
            },
            "Vendedor": {
                "Codigo": "V2",
                "Nombre": "ERIKA CEDE\u00d1O",
                "NumCajero": "V2"
            },
            "Comprador": {
                "TipoIdentificacion": "J",
                "NumeroIdentificacion": "412921533",
                "RazonSocial": "FARMACIA CENTRAL FAMA, C.A.",
                "Direccion": "AV. 93 (LISANDRO ALVARADO) CASA NUM. CIVICO 90-169 SECTOR FUNDO LA GUACAMAYA VALENCIA  CARABOBO",
                "Ubigeo": null,
                "Pais": "VE",
                "Notificar": null,
                "Telefono": [
                    "04144122949"
                ],
                "Correo": [
                    "",
                    "ventas.zona3@gruposolsumed.com"
                ],
                "OtrosEnvios": null
            },
            "SujetoRetenido": null,
            "Tercero": null,
            "Totales": {
                "NroItems": "6",
                "MontoGravadoTotal": "30686.43",
                "MontoExentoTotal": "3365.84",
                "Subtotal": "34052.27",
                "TotalIVA": "4909.83",
                "MontoTotalConIVA": "38962.10",
                "TotalAPagar": "38962.10",
                "TotalDescuento": "0.00",
                "SubtotalAntesDescuento": "34052.27",
                "MontoEnLetras": "",
                "ListaDescBonificacion": [],
                "ImpuestosSubtotal": [
                    {
                        "CodigoTotalImp": "G",
                        "AlicuotaImp": "16.00",
                        "BaseImponibleImp": "30686.43",
                        "ValorTotalImp": "4909.83"
                    },
                    {
                        "CodigoTotalImp": "E",
                        "AlicuotaImp": "0.00",
                        "BaseImponibleImp": "3365.84",
                        "ValorTotalImp": "0.00"
                    }
                ],
                "FormasPago": [
                    {
                        "Descripcion": "TRANSFERENCIA BANCARIA",
                        "Fecha": "17\/06\/2026",
                        "Forma": "03",
                        "Monto": "38962.10",
                        "Moneda": "VES",
                        "TipoCambio": "1.0000"
                    }
                ]
            },
            "TotalesOtraMoneda": {
                "Moneda": "USD",
                "TipoCambio": "596.7800",
                "MontoGravadoTotal": "51.42",
                "MontoExentoTotal": "5.64",
                "Subtotal": "57.06",
                "TotalAPagar": "65.29",
                "TotalIVA": "8.23",
                "MontoTotalConIVA": "65.29",
                "TotalDescuento": "0.00",
                "SubtotalAntesDescuento": "57.06",
                "MontoEnLetras": "",
                "ListaDescBonificacion": [],
                "ImpuestosSubtotal": [
                    {
                        "CodigoTotalImp": "G",
                        "AlicuotaImp": "16.00",
                        "BaseImponibleImp": "51.42",
                        "ValorTotalImp": "8.23"
                    },
                    {
                        "CodigoTotalImp": "E",
                        "AlicuotaImp": "0.00",
                        "BaseImponibleImp": "5.64",
                        "ValorTotalImp": "0.00"
                    }
                ],
                "FormasPago": [
                    {
                        "Descripcion": "TRANSFERENCIA BANCARIA",
                        "Fecha": "17\/06\/2026",
                        "Forma": "03",
                        "Monto": "65.29",
                        "Moneda": "USD",
                        "TipoCambio": "1.0000"
                    }
                ]
            }
        },
        "DetallesItems": [
            {
                "NumeroLinea": "1",
                "CodigoCIIU": "0198",
                "CodigoPLU": "CH-0057",
                "IndicadorBienoServicio": "1",
                "Descripcion": "APOSITO ALGINATO DE CALCIO 5 CM X 5 CM SOBRE 1 UND",
                "Cantidad": "2.00",
                "UnidadMedida": "UNI",
                "PrecioUnitario": "4.65",
                "PrecioItem": "9.30",
                "CodigoImpuesto": "G",
                "TasaIVA": "16.00",
                "ValorIVA": "1.49",
                "ValorTotalItem": "10.79",
                "InfoAdicionalItem": [
                    {
                        "campo": "Marca",
                        "valor": "EUROFARM"
                    }
                ]
            },
            {
                "NumeroLinea": "2",
                "CodigoCIIU": "0198",
                "CodigoPLU": "LEN-0030",
                "IndicadorBienoServicio": "1",
                "Descripcion": "CUBRE BOTAS 40G PAQ 50 PARES",
                "Cantidad": "2.00",
                "UnidadMedida": "UNI",
                "PrecioUnitario": "6.12",
                "PrecioItem": "12.24",
                "CodigoImpuesto": "G",
                "TasaIVA": "16.00",
                "ValorIVA": "1.96",
                "ValorTotalItem": "14.20",
                "InfoAdicionalItem": [
                    {
                        "campo": "Marca",
                        "valor": "ALTA MEDIC"
                    }
                ]
            },
            {
                "NumeroLinea": "3",
                "CodigoCIIU": "0198",
                "CodigoPLU": "LEN-0004",
                "IndicadorBienoServicio": "1",
                "Descripcion": "KIT DE PACIENTE SMS 40GR",
                "Cantidad": "6.00",
                "UnidadMedida": "UNI",
                "PrecioUnitario": "1.36",
                "PrecioItem": "8.16",
                "CodigoImpuesto": "G",
                "TasaIVA": "16.00",
                "ValorIVA": "1.31",
                "ValorTotalItem": "9.47",
                "InfoAdicionalItem": [
                    {
                        "campo": "Marca",
                        "valor": "ALTA MEDIC"
                    }
                ]
            },
            {
                "NumeroLinea": "4",
                "CodigoCIIU": "0198",
                "CodigoPLU": "MQD-0545",
                "IndicadorBienoServicio": "1",
                "Descripcion": "MASCARILLA KN95 BLANCA PAQ 10 UNDS",
                "Cantidad": "3.00",
                "UnidadMedida": "UNI",
                "PrecioUnitario": "1.88",
                "PrecioItem": "5.64",
                "CodigoImpuesto": "E",
                "TasaIVA": "0.00",
                "ValorIVA": "0.00",
                "ValorTotalItem": "5.64",
                "InfoAdicionalItem": [
                    {
                        "campo": "Marca",
                        "valor": "GENERICO"
                    }
                ]
            },
            {
                "NumeroLinea": "5",
                "CodigoCIIU": "0198",
                "CodigoPLU": "MEC-0011",
                "IndicadorBienoServicio": "1",
                "Descripcion": "MEDIAS DE COMPRESION 20-30MMHG A LA RODILLA TALLA L C\/ BEIG",
                "Cantidad": "1.00",
                "UnidadMedida": "UNI",
                "PrecioUnitario": "10.86",
                "PrecioItem": "10.86",
                "CodigoImpuesto": "G",
                "TasaIVA": "16.00",
                "ValorIVA": "1.74",
                "ValorTotalItem": "12.60",
                "InfoAdicionalItem": [
                    {
                        "campo": "Marca",
                        "valor": "BIALY"
                    }
                ]
            },
            {
                "NumeroLinea": "6",
                "CodigoCIIU": "0198",
                "CodigoPLU": "MEC-0012",
                "IndicadorBienoServicio": "1",
                "Descripcion": "MEDIAS DE COMPRESION 20-30MMHG A LA RODILLA TALLA XL C\/ BEIG",
                "Cantidad": "1.00",
                "UnidadMedida": "UNI",
                "PrecioUnitario": "10.86",
                "PrecioItem": "10.86",
                "CodigoImpuesto": "G",
                "TasaIVA": "16.00",
                "ValorIVA": "1.74",
                "ValorTotalItem": "12.60",
                "InfoAdicionalItem": [
                    {
                        "campo": "Marca",
                        "valor": "BIALY"
                    }
                ]
            }
        ],
        "DetallesRetencion": null,
        "Viajes": null,
        "InfoAdicional": [
            {
                "campo": "TransporteCliente",
                "valor": "INTERNO"
            },
            {
                "campo": "ZonaCliente",
                "valor": "CARABOBO"
            },
            {
                "campo": "DireccionEntregaCliente",
                "valor": "Grupo deus magnus"
            }
        ],
        "GuiaDespacho": null,
        "Transporte": null,
        "EsLote": null,
        "EsMinimo": null
    }
}