{
    "tasa_cambio": 563.29,
    "porcentaje_descuento": 0,
    "subtotal_usd": 145.7,
    "subtotal_antes_desc_ves": 82071.35,
    "monto_descuento_ves": 0,
    "monto_descuento_gravado_ves": 0,
    "monto_descuento_exento_ves": 0,
    "total_gravado_ves": 47513.51,
    "total_exento_ves": 34557.84,
    "suma_gravado_exento_ves": 82071.35,
    "subtotal_ves": 82071.35,
    "coinciden_ves": "SI",
    "total_iva_ves": 7602.16,
    "total_pagar_ves": 89673.51,
    "verificacion_5porciento": 4103.57,
    "diferencia_con_debug": 4103.57
}