{
    "tasa_cambio": 596.78,
    "porcentaje_descuento": 0,
    "subtotal_usd": 102.84,
    "subtotal_antes_desc_ves": 61372.86,
    "monto_descuento_ves": 0,
    "monto_descuento_gravado_ves": 0,
    "monto_descuento_exento_ves": 0,
    "total_gravado_ves": 38623.6,
    "total_exento_ves": 22749.25,
    "suma_gravado_exento_ves": 61372.85,
    "subtotal_ves": 61372.86,
    "coinciden_ves": "NO",
    "total_iva_ves": 6179.78,
    "total_pagar_ves": 67552.64,
    "verificacion_5porciento": 3068.64,
    "diferencia_con_debug": 3068.64
}